djangae/__init__.py
djangae/admin.py
djangae/apps.py
djangae/blobstore_service.py
djangae/checks.py
djangae/compat.py
djangae/crc64.py
djangae/deferred.py
djangae/environment.py
djangae/mail.py
djangae/models.py
djangae/noseplugin.py
djangae/processing.py
djangae/sandbox.py
djangae/settings_base.py
djangae/storage.py
djangae/test.py
djangae/test_runner.py
djangae/urls.py
djangae/utils.py
djangae/views.py
djangae/wsgi.py
djangae/contrib/__init__.py
djangae/contrib/sleuth.py
djangae/contrib/backup/__init__.py
djangae/contrib/backup/tasks.py
djangae/contrib/backup/urls.py
djangae/contrib/backup/utils.py
djangae/contrib/backup/views.py
djangae/contrib/backup/tests/__init__.py
djangae/contrib/backup/tests/test_tasks.py
djangae/contrib/backup/tests/test_utils.py
djangae/contrib/backup/tests/test_views.py
djangae/contrib/common/__init__.py
djangae/contrib/common/middleware.py
djangae/contrib/consistency/__init__.py
djangae/contrib/consistency/caches.py
djangae/contrib/consistency/consistency.py
djangae/contrib/consistency/models.py
djangae/contrib/consistency/signals.py
djangae/contrib/consistency/tests.py
djangae/contrib/contenttypes/__init__.py
djangae/contrib/contenttypes/apps.py
djangae/contrib/contenttypes/management.py
djangae/contrib/contenttypes/models.py
djangae/contrib/contenttypes/tests.py
djangae/contrib/contenttypes/migrations/0001_patch_contenttypes_migrations.py
djangae/contrib/contenttypes/migrations/0002_alter_id_field.py
djangae/contrib/contenttypes/migrations/__init__.py
djangae/contrib/gauth/__init__.py
djangae/contrib/gauth/backends.py
djangae/contrib/gauth/datastore.py
djangae/contrib/gauth/middleware.py
djangae/contrib/gauth/models.py
djangae/contrib/gauth/settings.py
djangae/contrib/gauth/sql.py
djangae/contrib/gauth/tests.py
djangae/contrib/gauth/urls.py
djangae/contrib/gauth/utils.py
djangae/contrib/gauth/validators.py
djangae/contrib/gauth/views.py
djangae/contrib/gauth/common/__init__.py
djangae/contrib/gauth/common/models.py
djangae-1.1.0.dist-info/LICENSE.md
djangae-1.1.0.dist-info/METADATA
djangae-1.1.0.dist-info/WHEEL
djangae-1.1.0.dist-info/top_level.txt
djangae-1.1.0.dist-info/RECORD
