Metadata-Version: 2.1
Name: djangae
Version: 1.1.0
Summary: Django integration with Google App Engine
Home-page: https://github.com/potatolondon/djangae
Author: Potato London Ltd.
Author-email: mail@p.ota.to
License: UNKNOWN
Keywords: django,Google App Engine,GAE
Platform: UNKNOWN
Classifier: Development Status :: 4 - Beta
Classifier: Framework :: Django
Classifier: Framework :: Django :: 1.8
Classifier: Framework :: Django :: 1.9
Classifier: Framework :: Django :: 1.10
Classifier: Framework :: Django :: 1.11
Classifier: Intended Audience :: Developers
Classifier: License :: OSI Approved :: BSD License
Classifier: Operating System :: OS Independent
Classifier: Programming Language :: Python
License-File: LICENSE.md
Provides-Extra: test
Requires-Dist: webtest ; extra == 'test'
